gicom/__init__.py
gicom/config.py
gicom/main.py
gicom-0.2.1.dist-info/licenses/LICENSE
gicom-0.2.1.dist-info/METADATA
gicom-0.2.1.dist-info/WHEEL
gicom-0.2.1.dist-info/entry_points.txt
gicom-0.2.1.dist-info/top_level.txt
gicom-0.2.1.dist-info/RECORD
