Metadata-Version: 2.4
Name: gicom
Version: 0.2.1
Summary: AI-powered Git commit messages generated directly from your terminal.
Home-page: https://github.com/amintorabi88/gicom
Author: Amin Torabi
License: MIT
Classifier: License :: OSI Approved :: MIT License
Classifier: Programming Language :: Python :: 3
Requires-Python: >=3.8
License-File: LICENSE
Requires-Dist: typer>=0.9
Requires-Dist: rich>=13
Requires-Dist: openai>=1.0.0
Requires-Dist: python-dotenv>=1.0.0
Requires-Dist: pyperclip
Dynamic: author
Dynamic: classifier
Dynamic: description
Dynamic: description-content-type
Dynamic: home-page
Dynamic: license
Dynamic: license-file
Dynamic: requires-dist
Dynamic: requires-python
Dynamic: summary
